pyblackscholesanalytics/__init__.py
pyblackscholesanalytics/example_bull_spread.py
pyblackscholesanalytics/example_bull_spread_other_params.py
pyblackscholesanalytics/example_calendar_spread.py
pyblackscholesanalytics/example_calendar_spread_other_params.py
pyblackscholesanalytics/example_options.py
pyblackscholesanalytics/example_options_IV.py
pyblackscholesanalytics/example_options_numeric_analytic_greeks_comparison.py
pyblackscholesanalytics/example_options_numeric_greeks.py
pyblackscholesanalytics/example_options_other_params.py
pyblackscholesanalytics/example_options_plot.py
pyblackscholesanalytics/example_options_plot_IV.py
pyblackscholesanalytics/example_options_plot_other_params.py
pyblackscholesanalytics/example_options_plot_surface.py
pyblackscholesanalytics/example_portfolio.py
pyblackscholesanalytics/example_portfolio_multi_strikes.py
pyblackscholesanalytics/example_portfolio_single_strike.py
pyblackscholesanalytics/market/__init__.py
pyblackscholesanalytics/market/market.py
pyblackscholesanalytics/options/__init__.py
pyblackscholesanalytics/options/options.py
pyblackscholesanalytics/plotter/__init__.py
pyblackscholesanalytics/plotter/plotter.py
pyblackscholesanalytics/portfolio/__init__.py
pyblackscholesanalytics/portfolio/portfolio.py
pyblackscholesanalytics/utils/__init__.py
pyblackscholesanalytics/utils/numeric_routines.py
pyblackscholesanalytics/utils/utils.py
tests/__init__.py
tests/test_options.py
tests/test_portfolio.py
pyBlackScholesAnalytics-0.0.2.dist-info/LICENSE
pyBlackScholesAnalytics-0.0.2.dist-info/METADATA
pyBlackScholesAnalytics-0.0.2.dist-info/WHEEL
pyBlackScholesAnalytics-0.0.2.dist-info/top_level.txt
pyBlackScholesAnalytics-0.0.2.dist-info/RECORD
