Metadata-Version: 2.1
Name: pyBlackScholesAnalytics
Version: 0.0.2
Summary: Options and Option Strategies analytics under the Black-Scholes Model for educational purpose
Home-page: https://github.com/gabrielepompa88/pyBlackScholesAnalytics
Author: Gabriele Pompa
Author-email: gabriele.pompa@gmail.com
License: UNKNOWN
Project-URL: Repository, https://github.com/gabrielepompa88/pyBlackScholesAnalytics
Keywords: finance black-scholes education
Platform: UNKNOWN
Classifier: Development Status :: 3 - Alpha
Classifier: Intended Audience :: Financial and Insurance Industry
Classifier: Intended Audience :: Education
Classifier: Intended Audience :: Science/Research
Classifier: Programming Language :: Python :: 3
Classifier: License :: OSI Approved :: MIT License
Classifier: Operating System :: OS Independent
Requires-Python: >=3.6
